django_debug_toolbar_django_info-0.3.0.dist-info/DESCRIPTION.rst
django_debug_toolbar_django_info-0.3.0.dist-info/METADATA
django_debug_toolbar_django_info-0.3.0.dist-info/RECORD
django_debug_toolbar_django_info-0.3.0.dist-info/WHEEL
django_debug_toolbar_django_info-0.3.0.dist-info/metadata.json
django_debug_toolbar_django_info-0.3.0.dist-info/top_level.txt
django_info_panel/__init__.py
django_info_panel/panels/__init__.py
django_info_panel/panels/database.py
django_info_panel/panels/template.py
django_info_panel/panels/urlpatterns.py
django_info_panel/templates/django_info/panels/database.html
django_info_panel/templates/django_info/panels/template.html
django_info_panel/templates/django_info/panels/template_table.html
django_info_panel/templates/django_info/panels/urlpatterns.html
