Metadata-Version: 2.0
Name: django-debug-toolbar-django-info
Version: 0.3.0
Summary: django-info panel for django-debug-toolbar
Home-page: https://github.com/jedie/django-debug-toolbar-django-info
Author: Jens Diemer
Author-email: UNKNOWN
License: UNKNOWN
Download-URL: https://github.com/jedie/django-debug-toolbar-django-info
Platform: UNKNOWN
Classifier: Development Status :: 5 - Production/Stable
Classifier: Environment :: Web Environment
Classifier: Intended Audience :: Developers
Classifier: License :: OSI Approved :: GNU General Public License (GPL)
Classifier: Programming Language :: Python
Classifier: Programming Language :: JavaScript
Classifier: Framework :: Django
Classifier: Topic :: Database :: Front-Ends
Classifier: Topic :: Documentation
Classifier: Topic :: Internet :: WWW/HTTP :: Dynamic Content
Classifier: Topic :: Internet :: WWW/HTTP :: Site Management
Classifier: Topic :: Internet :: WWW/HTTP :: WSGI :: Application
Classifier: Operating System :: OS Independent
Requires-Dist: django-debug-toolbar
